{
  "copyright_text": null,
  "description": "",
  "duration": 2625.0,
  "language": "eng",
  "recorded": "2020-07-23",
  "related_urls": [
    {
      "label": "Conference schedule",
      "url": "https://ep2020.europython.eu/schedule/"
    },
    {
      "label": "Conference Website",
      "url": "https://ep2020.europython.eu/"
    }
  ],
  "speakers": [],
  "tags": [
    "EuroPython2020"
  ],
  "thumbnail_url": "https://i.ytimg.com/vi/rkzXQOC1T0Q/hqdefault.jpg?sqp=-oaymwEZCNACELwBSFXyq4qpAwsIARUAAIhCGAFwAQ==&rs=AOn4CLDz5t11xamxxKgPxFlg8_wObhOolw",
  "title": "Abdur-Rahmaan Janhangeer - Django Clone From Scratch With Flask",
  "videos": [
    {
      "type": "youtube",
      "url": "https://www.youtube.com/watch?v=rkzXQOC1T0Q"
    }
  ]
}
